dl_data_pipeline/__init__.py
dl_data_pipeline/_version.py
dl_data_pipeline/deferred/__init__.py
dl_data_pipeline/deferred/deferred_wrapper.py
dl_data_pipeline/pipeline/__init__.py
dl_data_pipeline/pipeline/data_pipeline.py
dl_data_pipeline/pipeline/input_node.py
dl_data_pipeline/pipeline/pipe_node.py
dl_data_pipeline/process_functions/__init__.py
dl_data_pipeline/process_functions/any_process.py
dl_data_pipeline/process_functions/process_1d.py
dl_data_pipeline/process_functions/process_2d.py
dl_data_pipeline/validator/__init__.py
dl_data_pipeline/validator/base_validator.py
dl_data_pipeline/validator/mean_var_validator.py
dl_data_pipeline/validator/min_max_validator.py
dl_data_pipeline/validator/shape_validator.py
dl_data_pipeline/validator/type_validator.py
dl_data_pipeline/validator/validation_error.py
dl_data_pipeline-0.1.1.dist-info/METADATA
dl_data_pipeline-0.1.1.dist-info/WHEEL
dl_data_pipeline-0.1.1.dist-info/top_level.txt
dl_data_pipeline-0.1.1.dist-info/RECORD
