Metadata-Version: 2.1
Name: dl-data-pipeline
Version: 0.1.1
Summary: Easy pipeline to process datas.
Home-page: https://sacha-renault.github.io/DataPipeline/
Author: Sacha Renault
Author-email: 
Requires-Python: >=3.10
Requires-Dist: numpy>=1.26
Requires-Dist: opencv-python>=4.10.0
